pyflex/__init__.py
pyflex/config.py
pyflex/flexwin.py
pyflex/interval_scheduling.py
pyflex/stalta.py
pyflex/utils.py
pyflex/window.py
pyflex/window_selector.py
pyflex/tests/__init__.py
pyflex/tests/__main__.py
pyflex/tests/test_code_formatting.py
pyflex/tests/test_pyflex.py
pyflex/tests/test_utils.py
pyflex/tests/test_window.py
pyflex/tests/test_window_selector.py
pyflex-0.2.0.dist-info/LICENSE.txt
pyflex-0.2.0.dist-info/METADATA
pyflex-0.2.0.dist-info/WHEEL
pyflex-0.2.0.dist-info/top_level.txt
pyflex-0.2.0.dist-info/RECORD
