Metadata-Version: 2.1
Name: pyflex
Version: 0.2.0
Summary: Python port of the FLEXWIN package
Author: adjTomo Dev Team
Author-email: adjtomo@gmail.com
License: GNU GENERAL PUBLIC LICENSE
Project-URL: homepage, https://github.com/adjtomo/
Project-URL: documentation, https://adjtomo.github.io/pyflex
Project-URL: repository, https://github.com/adjtomo/pyflex
Requires-Python: >=3.7
License-File: LICENSE.txt
Requires-Dist: obspy
Provides-Extra: dev
Requires-Dist: pytest ; extra == 'dev'
Requires-Dist: ipython ; extra == 'dev'
Requires-Dist: ipdb ; extra == 'dev'
Requires-Dist: flake8 ; extra == 'dev'
Requires-Dist: nose ; extra == 'dev'
